beautifulscraper/__init__.py
beautifulscraper-1.1.1.data/data/share/doc/beautifulscraper-1.1.1/README
beautifulscraper-1.1.1.dist-info/METADATA
beautifulscraper-1.1.1.dist-info/WHEEL
beautifulscraper-1.1.1.dist-info/top_level.txt
beautifulscraper-1.1.1.dist-info/RECORD
