Metadata-Version: 1.0
Name: beautifulscraper
Version: 1.1.1
Summary: Python web-scraping library that wraps urllib2 and BeautifulSoup.
Home-page: https://github.com/adregner/beautifulscraper
Author: Andrew Regner
Author-email: andrew@aregner.com
License: MIT
Platform: UNKNOWN
